karaokehelper/__init__.py
karaokehelper/db.py
karaokehelper/example.py
karaokehelper/wabbit.py
karaokehelper-0.0.0.dev13.dist-info/LICENSE
karaokehelper-0.0.0.dev13.dist-info/METADATA
karaokehelper-0.0.0.dev13.dist-info/WHEEL
karaokehelper-0.0.0.dev13.dist-info/RECORD
