Metadata-Version: 2.3
Name: karaokehelper
Version: 0.0.0.dev13
Summary: This package is a collection of functions helpful for karaokebot
Author: Grumpy Chipmunk
Requires-Python: >=3.10,<4.0
Classifier: Programming Language :: Python :: 3
Classifier: Programming Language :: Python :: 3.10
Classifier: Programming Language :: Python :: 3.11
Classifier: Programming Language :: Python :: 3.12
Classifier: Programming Language :: Python :: 3.13
Requires-Dist: PyMySQL (>=1.0.2,<2.0.0)
Requires-Dist: cryptography (>=44.0.0,<45.0.0)
Requires-Dist: pika (>=1.3.1,<2.0.0)
Project-URL: CI, https://github.com/grumpychipmunk/karaokehelper/actions
Project-URL: Homepage, https://github.com/grumpychipmunk/karaokehelper
